wikinetworks/__init__.py
wikinetworks/wikinetworks.py
wikinetworks-1.1.2.dist-info/LICENSE
wikinetworks-1.1.2.dist-info/METADATA
wikinetworks-1.1.2.dist-info/WHEEL
wikinetworks-1.1.2.dist-info/top_level.txt
wikinetworks-1.1.2.dist-info/RECORD
