Metadata-Version: 2.1
Name: wikinetworks
Version: 1.1.2
Summary: A user-friendly Python package to process pathways from the WikiPathways database into machine-readable network representations.
Home-page: https://github.com/Thakar-Lab/WikiNetworks
Author: Mukta G. Palshikar
Author-email: muktapalshikar@gmail.com
License: UNKNOWN
Project-URL: Bug Tracker, https://github.com/Thakar-Lab/WikiNetworks/issues
Platform: UNKNOWN
Classifier: Programming Language :: Python :: 3
Classifier: License :: OSI Approved :: MIT License
Classifier: Operating System :: OS Independent
Classifier: Intended Audience :: Science/Research
Classifier: Natural Language :: English
Classifier: Topic :: Scientific/Engineering :: Bio-Informatics
Requires-Python: >=3.6
License-File: LICENSE
Requires-Dist: setuptools (>=57.4.0)
Requires-Dist: wheel (>=0.37.0)
Requires-Dist: pandas (>=1.1)
Requires-Dist: beautifulsoup4 (>=4)
Requires-Dist: requests (>=2)
Requires-Dist: bioservices (>=1.7)
Requires-Dist: numpy (>=1.19)
Requires-Dist: shapely (>=1.7)
Requires-Dist: scipy (>=1.5)
Requires-Dist: fiona (>=1.8)
Requires-Dist: pyproj (>=3)
Requires-Dist: rtree (>=0.9)
Requires-Dist: geopandas (>=0.9)
Requires-Dist: matplotlib (>=3)
Requires-Dist: seaborn (>=0.11.1)
Requires-Dist: networkx (==2.4)
